FourDExplorer/Constants.py
FourDExplorer/FourDExplorer.py
FourDExplorer/__init__.py
FourDExplorer/initial_config.py
FourDExplorer/bin/BlitManager.py
FourDExplorer/bin/ConfigManager.py
FourDExplorer/bin/DateTimeManager.py
FourDExplorer/bin/HDFManager.py
FourDExplorer/bin/Log.py
FourDExplorer/bin/MetaManager.py
FourDExplorer/bin/ResourceManager.py
FourDExplorer/bin/TabViewManager.py
FourDExplorer/bin/TaskManager.py
FourDExplorer/bin/UIManager.py
FourDExplorer/bin/UnitManager.py
FourDExplorer/bin/__init__.py
FourDExplorer/bin/app.py
FourDExplorer/bin/Actions/ControlActions.py
FourDExplorer/bin/Actions/DataActions.py
FourDExplorer/bin/Actions/EditActions.py
FourDExplorer/bin/Actions/FileActions.py
FourDExplorer/bin/Actions/FourDSTEMActions.py
FourDExplorer/bin/Actions/HelpActions.py
FourDExplorer/bin/Actions/MetaActions.py
FourDExplorer/bin/Actions/PlotActions.py
FourDExplorer/bin/Actions/VectorFieldActions.py
FourDExplorer/bin/Actions/__init__.py
FourDExplorer/bin/MetaManagers/MetaTrees.py
FourDExplorer/bin/MetaManagers/MetadataFields.py
FourDExplorer/bin/MetaManagers/__init__.py
FourDExplorer/bin/Widgets/DialogAbout.py
FourDExplorer/bin/Widgets/DialogAddMeta.py
FourDExplorer/bin/Widgets/DialogAdjustPatchEffects.py
FourDExplorer/bin/Widgets/DialogAttrViewer.py
FourDExplorer/bin/Widgets/DialogChangeDataType.py
FourDExplorer/bin/Widgets/DialogChooseItem.py
FourDExplorer/bin/Widgets/DialogCopyItem.py
FourDExplorer/bin/Widgets/DialogCreateItem.py
FourDExplorer/bin/Widgets/DialogDeleteMeta.py
FourDExplorer/bin/Widgets/DialogEditMeta.py
FourDExplorer/bin/Widgets/DialogEditParaFourDSTEM.py
FourDExplorer/bin/Widgets/DialogFindRotationAngle.py
FourDExplorer/bin/Widgets/DialogHistoryTasks.py
FourDExplorer/bin/Widgets/DialogImportFourDSTEM.py
FourDExplorer/bin/Widgets/DialogImportImage.py
FourDExplorer/bin/Widgets/DialogMetaViewer.py
FourDExplorer/bin/Widgets/DialogMoveItem.py
FourDExplorer/bin/Widgets/DialogSaveFourDSTEM.py
FourDExplorer/bin/Widgets/DialogSaveItem.py
FourDExplorer-0.6.5.dist-info/LICENSE
FourDExplorer-0.6.5.dist-info/METADATA
FourDExplorer-0.6.5.dist-info/WHEEL
FourDExplorer-0.6.5.dist-info/top_level.txt
FourDExplorer-0.6.5.dist-info/RECORD
