Metadata-Version: 2.1
Name: FourDExplorer
Version: 0.6.5
Summary: Use 4D-Explorer to process and analyze 4D-STEM data.
Home-page: https://github.com/ManifoldsHu/FourDExplorer
Author: Hu Yiming
Author-email: FourDExplorer@gmail.com
License: GPLv3
Classifier: License :: OSI Approved :: GNU General Public License v3 (GPLv3)
Classifier: Development Status :: 3 - Alpha
Classifier: Intended Audience :: Science/Research
Classifier: Natural Language :: English
Classifier: Operating System :: OS Independent
Classifier: Programming Language :: Python :: 3
Classifier: Programming Language :: Python :: 3.10
Classifier: Programming Language :: Python :: Implementation :: CPython
Classifier: Topic :: Scientific/Engineering :: Physics
Classifier: Topic :: Scientific/Engineering :: Chemistry
Requires-Python: >=3.10.1,<3.11
License-File: LICENSE
Requires-Dist: h5py >=3.8
Requires-Dist: matplotlib <3.9,>=3.8
Requires-Dist: numpy <2.0,>=1.21
Requires-Dist: onnxruntime >=1.18
Requires-Dist: Pillow >=10.0
Requires-Dist: Pint >=0.22
Requires-Dist: psutil >=5.9.0
Requires-Dist: pyinstaller >=6.10
Requires-Dist: PySide6 ==6.2.2.1
Requires-Dist: qt-material ==2.12
Requires-Dist: scikit-image >=0.20.0
Requires-Dist: scipy >=1.9.0
Requires-Dist: Sphinx >=7.4.7
Requires-Dist: sphinx-rtd-theme >=2.0.0
Requires-Dist: sphinxcontrib-applehelp >=2.0.0
Requires-Dist: sphinxcontrib-devhelp >=2.0.0
Requires-Dist: sphinxcontrib-htmlhelp >=2.0.0
Requires-Dist: sphinxcontrib-jquery >=4.1
Requires-Dist: sphinxcontrib-jsmath >=1.0.1
Requires-Dist: sphinxcontrib-qthelp >=2.0.0
Requires-Dist: sphinxcontrib-serializinghtml >=2.0.0
Requires-Dist: twine >=4.8
